LICENSE.txt
README.md
setup.cfg
setup.py
src/FeaSel_Net.egg-info/PKG-INFO
src/FeaSel_Net.egg-info/SOURCES.txt
src/FeaSel_Net.egg-info/dependency_links.txt
src/FeaSel_Net.egg-info/requires.txt
src/FeaSel_Net.egg-info/top_level.txt
src/feasel/__init__.py
src/feasel/data/__init__.py
src/feasel/data/classification.py
src/feasel/data/filter.py
src/feasel/data/metrics.py
src/feasel/data/normalize.py
src/feasel/data/preprocess.py
src/feasel/data/regression.py
src/feasel/linear/__init__.py
src/feasel/linear/base.py
src/feasel/linear/lda.py
src/feasel/linear/pca.py
src/feasel/linear/svd.py
src/feasel/nn/__init__.py
src/feasel/nn/analysis.py
src/feasel/nn/architectures.py
src/feasel/nn/tfcustom/__init__.py
src/feasel/nn/tfcustom/callbacks.py
src/feasel/nn/tfcustom/layers.py
src/feasel/nn/tfcustom/utils/__init__.py
src/feasel/nn/tfcustom/utils/callback/__init__.py
src/feasel/nn/tfcustom/utils/callback/log.py
src/feasel/nn/tfcustom/utils/callback/trigger.py
src/feasel/parameter/__init__.py
src/feasel/parameter/base.py
src/feasel/parameter/build.py
src/feasel/parameter/callback.py
src/feasel/parameter/data.py
src/feasel/parameter/params.py
src/feasel/parameter/train.py
src/feasel/plot/__init__.py
src/feasel/plot/base.py
src/feasel/plot/feasel.py
src/feasel/plot/linear_transformation.py
src/feasel/plot/neural_network.py
src/feasel/plot/utils/__init__.py
src/feasel/plot/utils/_default.py
src/feasel/plot/utils/_utils.py
src/feasel/plot/utils/_visualization.py
src/feasel/utils/__init__.py
src/feasel/utils/log.py
src/feasel/utils/syntax.py
src/feasel/utils/time.py