Metadata-Version: 2.1
Name: FeaSel-Net
Version: 0.0.9
Summary: A Keras callback package for iteratively selecting the most influential input nodes during training.
Home-page: https://github.tik.uni-stuttgart.de/FelixFischer/FeaSel-Net.git
Author: Felix Fischer
Author-email: felix.fischer@ito.uni-stuttgart.de
License: MIT
Keywords: feature selection,neural networksmachine learning
Platform: UNKNOWN
Classifier: Programming Language :: Python :: 3
Classifier: Programming Language :: Python :: 3.6
Classifier: Programming Language :: Python :: 3.7
Classifier: Programming Language :: Python :: 3.8
Classifier: Programming Language :: Python :: 3.9
Classifier: Development Status :: 4 - Beta
Classifier: License :: OSI Approved :: MIT License
Classifier: Operating System :: OS Independent
Requires-Python: >=3.7
License-File: LICENSE.txt
